[
  {
    "horizon": "1week",
    "horizon_label": "1주 후",
    "lag_weeks": 1,
    "channel": "Offline",
    "n_features": 56,
    "train_n": 8872,
    "test_n": 3057,
    "xgb_R2": 0.6951,
    "lgb_R2": 0.6954,
    "lgb_weight": 0.45,
    "RMSE": 157499.0,
    "NRMSE": 0.625,
    "R2": 0.6962,
    "MAPE": 200.0
  },
  {
    "horizon": "1week",
    "horizon_label": "1주 후",
    "lag_weeks": 1,
    "channel": "Online",
    "n_features": 56,
    "train_n": 7318,
    "test_n": 2560,
    "xgb_R2": 0.8456,
    "lgb_R2": 0.8464,
    "lgb_weight": 0.5,
    "RMSE": 191815.0,
    "NRMSE": 0.456,
    "R2": 0.8469,
    "MAPE": 58.7
  },
  {
    "horizon": "1week",
    "horizon_label": "1주 후",
    "lag_weeks": 1,
    "channel": "Total",
    "n_features": 56,
    "train_n": 9228,
    "test_n": 3185,
    "xgb_R2": 0.8493,
    "lgb_R2": 0.851,
    "lgb_weight": 0.8500000000000001,
    "RMSE": 264716.0,
    "NRMSE": 0.456,
    "R2": 0.851,
    "MAPE": 166.2
  },
  {
    "horizon": "1month",
    "horizon_label": "1개월 후",
    "lag_weeks": 4,
    "channel": "Offline",
    "n_features": 56,
    "train_n": 8333,
    "test_n": 2795,
    "xgb_R2": 0.6819,
    "lgb_R2": 0.6843,
    "lgb_weight": 0.7000000000000001,
    "RMSE": 160149.0,
    "NRMSE": 0.636,
    "R2": 0.6844,
    "MAPE": 162.7
  },
  {
    "horizon": "1month",
    "horizon_label": "1개월 후",
    "lag_weeks": 4,
    "channel": "Online",
    "n_features": 56,
    "train_n": 6870,
    "test_n": 2356,
    "xgb_R2": 0.8388,
    "lgb_R2": 0.8392,
    "lgb_weight": 0.55,
    "RMSE": 195809.0,
    "NRMSE": 0.466,
    "R2": 0.8399,
    "MAPE": 60.6
  },
  {
    "horizon": "1month",
    "horizon_label": "1개월 후",
    "lag_weeks": 4,
    "channel": "Total",
    "n_features": 56,
    "train_n": 8687,
    "test_n": 2916,
    "xgb_R2": 0.8422,
    "lgb_R2": 0.8398,
    "lgb_weight": 0.0,
    "RMSE": 271647.0,
    "NRMSE": 0.468,
    "R2": 0.8422,
    "MAPE": 135.0
  },
  {
    "horizon": "3months",
    "horizon_label": "3개월 후",
    "lag_weeks": 13,
    "channel": "Offline",
    "n_features": 56,
    "train_n": 6115,
    "test_n": 2727,
    "xgb_R2": 0.6633,
    "lgb_R2": 0.6558,
    "lgb_weight": 0.0,
    "RMSE": 166217.0,
    "NRMSE": 0.647,
    "R2": 0.6633,
    "MAPE": 156.6
  },
  {
    "horizon": "3months",
    "horizon_label": "3개월 후",
    "lag_weeks": 13,
    "channel": "Online",
    "n_features": 56,
    "train_n": 5006,
    "test_n": 2327,
    "xgb_R2": 0.8464,
    "lgb_R2": 0.8408,
    "lgb_weight": 0.0,
    "RMSE": 192378.0,
    "NRMSE": 0.454,
    "R2": 0.8464,
    "MAPE": 58.4
  },
  {
    "horizon": "3months",
    "horizon_label": "3개월 후",
    "lag_weeks": 13,
    "channel": "Total",
    "n_features": 56,
    "train_n": 6432,
    "test_n": 2854,
    "xgb_R2": 0.8335,
    "lgb_R2": 0.8363,
    "lgb_weight": 0.8,
    "RMSE": 277865.0,
    "NRMSE": 0.469,
    "R2": 0.8363,
    "MAPE": 119.3
  }
]